fastapi_simple_class_view/__init__.py
fastapi_simple_class_view/abc.py
fastapi_simple_class_view/base.py
fastapi_simple_class_view/controller.py
fastapi_simple_class_view/meta.py
fastapi_simple_class_view/mixins.py
fastapi_simple_class_view/type.py
fastapi_simple_class_view-0.0.3.dist-info/METADATA
fastapi_simple_class_view-0.0.3.dist-info/WHEEL
fastapi_simple_class_view-0.0.3.dist-info/licenses/LICENSE
fastapi_simple_class_view-0.0.3.dist-info/RECORD
