Metadata-Version: 2.1
Name: fastapi_simple_class_view
Version: 0.0.3
Summary: Class based view for FastAPI
Project-URL: Homepage, https://github.com/gravity48/fastapi_class_view
Project-URL: Bug Tracker, https://github.com/gravity48/fastapi_class_view/issues
Author-email: gravity48 <gravity4849@gmail.com>
License-File: LICENSE
Classifier: License :: OSI Approved :: MIT License
Classifier: Operating System :: OS Independent
Classifier: Programming Language :: Python :: 3
Requires-Python: >=3.10
Requires-Dist: fastapi>=0.98.0
Requires-Dist: pydantic>=2.0.3
